{
  "address": "B1cHVNAFWYX3zXZjqi2tubPZGzrLQEAiL5A9URqKskFi",
  "metadata": {
    "name": "anaheim",
    "version": "0.1.0",
    "spec": "0.1.0",
    "description": "Created with Anchor"
  },
  "instructions": [
    {
      "name": "decrement",
      "discriminator": [
        106,
        227,
        168,
        59,
        248,
        27,
        150,
        101
      ],
      "accounts": [
        {
          "name": "anaheim_account",
          "writable": true,
          "pda": {
            "seeds": [
              {
                "kind": "const",
                "value": [
                  97,
                  110,
                  97,
                  104,
                  101,
                  105,
                  109
                ]
              },
              {
                "kind": "account",
                "path": "authority"
              }
            ]
          }
        },
        {
          "name": "authority",
          "signer": true,
          "relations": [
            "anaheim_account"
          ]
        }
      ],
      "args": []
    },
    {
      "name": "increment",
      "discriminator": [
        11,
        18,
        104,
        9,
        104,
        174,
        59,
        33
      ],
      "accounts": [
        {
          "name": "anaheim_account",
          "writable": true,
          "pda": {
            "seeds": [
              {
                "kind": "const",
                "value": [
                  97,
                  110,
                  97,
                  104,
                  101,
                  105,
                  109
                ]
              },
              {
                "kind": "account",
                "path": "authority"
              }
            ]
          }
        },
        {
          "name": "authority",
          "signer": true,
          "relations": [
            "anaheim_account"
          ]
        }
      ],
      "args": []
    },
    {
      "name": "initialize",
      "discriminator": [
        175,
        175,
        109,
        31,
        13,
        152,
        155,
        237
      ],
      "accounts": [
        {
          "name": "anaheim_account",
          "writable": true,
          "pda": {
            "seeds": [
              {
                "kind": "const",
                "value": [
                  97,
                  110,
                  97,
                  104,
                  101,
                  105,
                  109
                ]
              },
              {
                "kind": "account",
                "path": "payer"
              }
            ]
          }
        },
        {
          "name": "payer",
          "writable": true,
          "signer": true
        },
        {
          "name": "system_program",
          "address": "11111111111111111111111111111111"
        }
      ],
      "args": []
    },
    {
      "name": "set",
      "discriminator": [
        198,
        51,
        53,
        241,
        116,
        29,
        126,
        194
      ],
      "accounts": [
        {
          "name": "anaheim_account",
          "writable": true,
          "pda": {
            "seeds": [
              {
                "kind": "const",
                "value": [
                  97,
                  110,
                  97,
                  104,
                  101,
                  105,
                  109
                ]
              },
              {
                "kind": "account",
                "path": "authority"
              }
            ]
          }
        },
        {
          "name": "authority",
          "signer": true,
          "relations": [
            "anaheim_account"
          ]
        }
      ],
      "args": [
        {
          "name": "value",
          "type": "u64"
        }
      ]
    }
  ],
  "accounts": [
    {
      "name": "AnaheimAccount",
      "discriminator": [
        26,
        253,
        236,
        239,
        22,
        181,
        47,
        158
      ]
    }
  ],
  "types": [
    {
      "name": "AnaheimAccount",
      "type": {
        "kind": "struct",
        "fields": [
          {
            "name": "authority",
            "type": "pubkey"
          },
          {
            "name": "bump",
            "type": "u8"
          },
          {
            "name": "count",
            "type": "u64"
          }
        ]
      }
    }
  ]
}